etl_manager/__init__.py
etl_manager/etl.py
etl_manager/meta.py
etl_manager/specs/avro_specific.json
etl_manager/specs/base.json
etl_manager/specs/csv_quoted_nodate_specific.json
etl_manager/specs/csv_specific.json
etl_manager/specs/glue_job.json
etl_manager/specs/glue_spark_dict.json
etl_manager/specs/json_specific.json
etl_manager/specs/orc_specific.json
etl_manager/specs/parquet_specific.json
etl_manager/specs/regex_specific.json
etl_manager/specs/table_schema.json
etl_manager/utils.py
etl_manager-9.0.2.dist-info/METADATA
etl_manager-9.0.2.dist-info/WHEEL
etl_manager-9.0.2.dist-info/RECORD
