Metadata-Version: 2.4
Name: etl_manager
Version: 9.0.2
Summary: A python package to manage etl processes on AWS
License: MIT
Author: Karik Isichei
Author-email: karik.isichei@digital.justice.gov.uk
Requires-Python: >=3.9,<4.0
Classifier: License :: OSI Approved :: MIT License
Classifier: Programming Language :: Python :: 3
Classifier: Programming Language :: Python :: 3.9
Classifier: Programming Language :: Python :: 3.10
Classifier: Programming Language :: Python :: 3.11
Classifier: Programming Language :: Python :: 3.12
Classifier: Programming Language :: Python :: 3.13
Classifier: Programming Language :: Python :: 3.14
Requires-Dist: boto3 (>=1.9.205)
Requires-Dist: jsonschema (>=3.0.0)
Requires-Dist: parameterized (==0.7.*)
Requires-Dist: regex (>=2020.7.14)
Requires-Dist: setuptools (>=80.10.1)
